append.py
append-1.0.2.dist-info/METADATA
append-1.0.2.dist-info/WHEEL
append-1.0.2.dist-info/entry_points.txt
append-1.0.2.dist-info/top_level.txt
append-1.0.2.dist-info/RECORD
