Metadata-Version: 2.1
Name: append
Version: 1.0.2
Summary: A simple tool to add a string to the start or end of every line in a text file.
Home-page: https://github.com/4nk1t/append
Author: Ankit
Author-email: ashuankitpandey@gmail.com
Classifier: Programming Language :: Python :: 3
Classifier: License :: OSI Approved :: MIT License
Classifier: Operating System :: OS Independent
Requires-Python: >=3.6
